fakestockdata/__init__.py
fakestockdata/core.py
fakestockdata-0.0.2.data/data/share/fakestockdata/daily/table_aa.csv.bz2
fakestockdata-0.0.2.data/data/share/fakestockdata/daily/table_aapl.csv.bz2
fakestockdata-0.0.2.data/data/share/fakestockdata/daily/table_abc.csv.bz2
fakestockdata-0.0.2.data/data/share/fakestockdata/daily/table_aig.csv.bz2
fakestockdata-0.0.2.data/data/share/fakestockdata/daily/table_amgn.csv.bz2
fakestockdata-0.0.2.data/data/share/fakestockdata/daily/table_amzn.csv.bz2
fakestockdata-0.0.2.data/data/share/fakestockdata/daily/table_bwa.csv.bz2
fakestockdata-0.0.2.data/data/share/fakestockdata/daily/table_cost.csv.bz2
fakestockdata-0.0.2.data/data/share/fakestockdata/daily/table_csco.csv.bz2
fakestockdata-0.0.2.data/data/share/fakestockdata/daily/table_d.csv.bz2
fakestockdata-0.0.2.data/data/share/fakestockdata/daily/table_ebay.csv.bz2
fakestockdata-0.0.2.data/data/share/fakestockdata/daily/table_emr.csv.bz2
fakestockdata-0.0.2.data/data/share/fakestockdata/daily/table_esrx.csv.bz2
fakestockdata-0.0.2.data/data/share/fakestockdata/daily/table_gas.csv.bz2
fakestockdata-0.0.2.data/data/share/fakestockdata/daily/table_ge.csv.bz2
fakestockdata-0.0.2.data/data/share/fakestockdata/daily/table_goog.csv.bz2
fakestockdata-0.0.2.data/data/share/fakestockdata/daily/table_hal.csv.bz2
fakestockdata-0.0.2.data/data/share/fakestockdata/daily/table_hp.csv.bz2
fakestockdata-0.0.2.data/data/share/fakestockdata/daily/table_hpq.csv.bz2
fakestockdata-0.0.2.data/data/share/fakestockdata/daily/table_ibm.csv.bz2
fakestockdata-0.0.2.data/data/share/fakestockdata/daily/table_jbl.csv.bz2
fakestockdata-0.0.2.data/data/share/fakestockdata/daily/table_jpm.csv.bz2
fakestockdata-0.0.2.data/data/share/fakestockdata/daily/table_met.csv.bz2
fakestockdata-0.0.2.data/data/share/fakestockdata/daily/table_nyx.csv.bz2
fakestockdata-0.0.2.data/data/share/fakestockdata/daily/table_pcg.csv.bz2
fakestockdata-0.0.2.dist-info/DESCRIPTION.rst
fakestockdata-0.0.2.dist-info/METADATA
fakestockdata-0.0.2.dist-info/RECORD
fakestockdata-0.0.2.dist-info/WHEEL
fakestockdata-0.0.2.dist-info/metadata.json
fakestockdata-0.0.2.dist-info/top_level.txt
