Metadata-Version: 2.0
Name: fakestockdata
Version: 0.0.2
Summary: Generate CSV data for stocks
Home-page: http://github.com/mrocklin/fakestockdata/
Author: Matthew Rocklin
Author-email: mrocklin@gmail.com
License: BSD
Platform: UNKNOWN
